cob_arcgis_geocoder/__init__.py
cob_arcgis_geocoder/geocode.py
cob_arcgis_geocoder/test.py
cob_arcgis_geocoder-0.0.2.dist-info/LICENSE
cob_arcgis_geocoder-0.0.2.dist-info/METADATA
cob_arcgis_geocoder-0.0.2.dist-info/WHEEL
cob_arcgis_geocoder-0.0.2.dist-info/top_level.txt
cob_arcgis_geocoder-0.0.2.dist-info/RECORD
