Metadata-Version: 2.1
Name: cob-arcgis-geocoder
Version: 0.0.2
Summary: Python geocoder to be used in ETL pipelines
Home-page: https://github.com/CityOfBoston/cob_arcgis_geocoder
Author: Analytics Team
Author-email: analytics@boston.gov
License: UNKNOWN
Platform: UNKNOWN
